skboost/__init__.py
skboost/evaluation/__init__.py
skboost/evaluation/confidence.py
skboost/preprocessing/__init__.py
skboost/preprocessing/dual_scaler.py
skboost/preprocessing/group.py
skboost/preprocessing/relational.py
skboost/tuning/__init__.py
skboost/tuning/zoom_search.py
skboost-0.2.0.dist-info/licenses/LICENSE
skboost-0.2.0.dist-info/METADATA
skboost-0.2.0.dist-info/WHEEL
skboost-0.2.0.dist-info/top_level.txt
skboost-0.2.0.dist-info/RECORD
