Metadata-Version: 2.4
Name: skboost
Version: 0.2.0
Summary: Relational features, adaptive search, and confidence evaluation tools for scikit-learn
Author-email: Oluwaseyi Shoboyejo <sunmark130@gmail.com>
License: MIT
Project-URL: Homepage, https://github.com/mksunny1/skboost
Project-URL: Repository, https://github.com/mksunny1/skboost
Classifier: Development Status :: 4 - Beta
Classifier: Programming Language :: Python :: 3
Classifier: Programming Language :: Python :: 3.8
Classifier: Programming Language :: Python :: 3.9
Classifier: Programming Language :: Python :: 3.10
Classifier: Programming Language :: Python :: 3.11
Classifier: License :: OSI Approved :: MIT License
Classifier: Operating System :: OS Independent
Classifier: Intended Audience :: Science/Research
Classifier: Topic :: Scientific/Engineering :: Artificial Intelligence
Requires-Python: >=3.8
License-File: LICENSE
Requires-Dist: numpy
Requires-Dist: pandas
Requires-Dist: scikit-learn>=0.24
Requires-Dist: matplotlib
Dynamic: license-file
